nomadlad/__init__.py
nomadlad/_nomadlad_bridge.cpython-314-x86_64-linux-gnu.so
nomadlad-1.1.0.dist-info/METADATA
nomadlad-1.1.0.dist-info/WHEEL
nomadlad-1.1.0.dist-info/top_level.txt
nomadlad-1.1.0.dist-info/RECORD
nomadlad-1.1.0.dist-info/licenses/LICENSE
