Metadata-Version: 2.4
Name: nomadlad
Version: 1.1.0
Summary: Interface for NOMAD 4.5.1 blackbox optimization software.
Home-page: https://github.com/jan-provaznik/nomadlad
Author: Jan Provaznik
Author-email: jan@provaznik.pro
License: LGPL-3.0
License-File: LICENSE
Dynamic: author
Dynamic: author-email
Dynamic: description
Dynamic: description-content-type
Dynamic: home-page
Dynamic: license
Dynamic: license-file
Dynamic: summary
